[
  {
    "batch_number": 19,
    "node_count": 44,
    "node_ids": [
      "everything-else",
      "buyer",
      "notifications",
      "order-management",
      "payment",
      "seller-tools",
      "sellertools",
      "services",
      "stores",
      "support",
      "sustainability",
      "tax",
      "verticals",
      "1-day-handling",
      "1099-k-tax-form",
      "2-step-verification",
      "30-day-returns",
      "360-spin",
      "60-day-returns",
      "above-standard",
      "above-standard-status",
      "accept-offer",
      "accept-return",
      "account-management-plus",
      "account-management-premium",
      "account-security",
      "account-settings",
      "account-suspended",
      "account-suspension",
      "active-content-policy",
      "active-listings",
      "ad-attribution",
      "ad-fee",
      "ad-rate-recommendation",
      "add-payment-method",
      "add-to-cart",
      "add-to-watch-list",
      "add-to-watchlist",
      "advanced-listing-tool",
      "advanced-listing-tool-multi-market",
      "advanced-search",
      "ai-banner",
      "ai-snap",
      "anniversary-sale"
    ],
    "program_list": "1. Everything Else / Cross-Category (node_id: everything-else)\n2. Buyer (node_id: buyer)\n3. Notifications (node_id: notifications)\n4. Order Management (node_id: order-management)\n5. Payment (node_id: payment)\n6. Seller Tools (node_id: seller-tools)\n7. Seller Tools (node_id: sellertools)\n8. Services (node_id: services)\n9. Stores (node_id: stores)\n10. Support (node_id: support)\n11. Sustainability (node_id: sustainability)\n12. Tax (node_id: tax)\n13. Verticals (node_id: verticals)\n14. 1-Day Handling (node_id: 1-day-handling)\n15. 1099-K Tax Form (node_id: 1099-k-tax-form)\n16. 2-Step Verification (node_id: 2-step-verification)\n17. 30-Day Returns (node_id: 30-day-returns)\n18. 360 Spin (node_id: 360-spin)\n19. 60-Day Returns (node_id: 60-day-returns)\n20. Above Standard (node_id: above-standard)\n21. Above Standard (node_id: above-standard-status)\n22. Accept Offer (node_id: accept-offer)\n23. Accept Return (node_id: accept-return)\n24. Account Management Plus (node_id: account-management-plus)\n25. Account Management Premium (node_id: account-management-premium)\n26. Account Security (node_id: account-security)\n27. Account Settings (node_id: account-settings)\n28. Account Suspended (node_id: account-suspended)\n29. Account Suspension (node_id: account-suspension)\n30. Active Content Policy (node_id: active-content-policy)\n31. Active Listings (node_id: active-listings)\n32. Ad Attribution (node_id: ad-attribution)\n33. Ad Fee (node_id: ad-fee)\n34. Ad Rate Recommendation (node_id: ad-rate-recommendation)\n35. Add Payment Method (node_id: add-payment-method)\n36. Add to Cart (node_id: add-to-cart)\n37. Add to Watch List (node_id: add-to-watch-list)\n38. Add to Watchlist (node_id: add-to-watchlist)\n39. Advanced Listing Tool (node_id: advanced-listing-tool)\n40. Advanced Listing Tool (node_id: advanced-listing-tool-multi-market)\n41. Advanced Search (node_id: advanced-search)\n42. AI Banner (node_id: ai-banner)\n43. AI Snap (node_id: ai-snap)\n44. Anniversary Sale (node_id: anniversary-sale)"
  },
  {
    "batch_number": 20,
    "node_count": 44,
    "node_ids": [
      "antiques",
      "app-store-promotion",
      "ask-question",
      "auction-ended",
      "auction-style-listings",
      "auction-style-listings-multi-market",
      "augmented-reality-preview",
      "authenticator-app",
      "authenticity-guarantee-filter",
      "authenticity-guarantee-multi-market",
      "authenticity-guarantee-streetwear",
      "authorized-seller-filter",
      "auto-pricing",
      "auto-relist",
      "automatic-relisting",
      "awaiting-shipment",
      "back-in-stock",
      "back-to-school",
      "below-standard-status",
      "best-match-multi-market",
      "best-match-sort",
      "bid-now",
      "bid-shielding-policy",
      "bidding",
      "bids-and-offers",
      "biometric-verification",
      "block-buyers",
      "bold",
      "bold-title",
      "bons-plans-fr",
      "bounce-rate",
      "brand-identity",
      "brand-name",
      "bulk-listing-tool-multi-market",
      "bulk-listing-tools",
      "bulk-listing-upload",
      "buy-it-now-filter",
      "certified-recycled",
      "certified-recycler-program",
      "classified-ads",
      "clear-filters",
      "click-and-collect",
      "click-and-collect-multi-market",
      "click-collect"
    ],
    "program_list": "1. Antiques (node_id: antiques)\n2. App Store Promotion (node_id: app-store-promotion)\n3. Ask Question (node_id: ask-question)\n4. Auction Ended (node_id: auction-ended)\n5. Auction-Style Listings (node_id: auction-style-listings)\n6. Auction-Style Listings (node_id: auction-style-listings-multi-market)\n7. Augmented Reality Preview (node_id: augmented-reality-preview)\n8. Authenticator App (node_id: authenticator-app)\n9. Authenticity Guarantee Filter (node_id: authenticity-guarantee-filter)\n10. Authenticity Guarantee (node_id: authenticity-guarantee-multi-market)\n11. Authenticity Guarantee - Streetwear (node_id: authenticity-guarantee-streetwear)\n12. Authorized Seller Filter (node_id: authorized-seller-filter)\n13. Auto Pricing (node_id: auto-pricing)\n14. Auto-Relist (node_id: auto-relist)\n15. Automatic Relisting (node_id: automatic-relisting)\n16. Awaiting Shipment (node_id: awaiting-shipment)\n17. Back in Stock (node_id: back-in-stock)\n18. Back to School (node_id: back-to-school)\n19. Below Standard (node_id: below-standard-status)\n20. Best Match (Cassini) (node_id: best-match-multi-market)\n21. Best Match Sort (node_id: best-match-sort)\n22. Bid Now (node_id: bid-now)\n23. Bid Shielding Policy (node_id: bid-shielding-policy)\n24. Bidding (node_id: bidding)\n25. Bids & Offers (node_id: bids-and-offers)\n26. Biometric Verification (node_id: biometric-verification)\n27. Block Buyers (node_id: block-buyers)\n28. Bold (node_id: bold)\n29. Bold Title (node_id: bold-title)\n30. Bons Plans (node_id: bons-plans-fr)\n31. Bounce Rate (node_id: bounce-rate)\n32. Brand Identity (node_id: brand-identity)\n33. Brand Name (node_id: brand-name)\n34. Bulk Listing Tool (node_id: bulk-listing-tool-multi-market)\n35. Bulk Listing Tools (node_id: bulk-listing-tools)\n36. Bulk Listing Upload (node_id: bulk-listing-upload)\n37. Buy It Now Filter (node_id: buy-it-now-filter)\n38. Certified Recycled (node_id: certified-recycled)\n39. Certified Recycler Program (node_id: certified-recycler-program)\n40. Classified Ads (node_id: classified-ads)\n41. Clear Filters (node_id: clear-filters)\n42. Click & Collect (node_id: click-and-collect)\n43. Click & Collect (node_id: click-and-collect-multi-market)\n44. Click & Collect (node_id: click-collect)"
  },
  {
    "batch_number": 21,
    "node_count": 44,
    "node_ids": [
      "click-through-rate",
      "coded-coupons",
      "coded-coupons-multi-market",
      "codeless-coupons",
      "coins-currency",
      "collectibles-price-guide",
      "collection-points-au",
      "collections",
      "combined-checkout",
      "comics",
      "condition-filter",
      "condition-new-sort",
      "curated-lists",
      "custom-template",
      "delivered",
      "delivery-updates",
      "description-template",
      "detailed-seller-ratings-multi-market",
      "dhl-paket",
      "discounts-manager",
      "discounts-manager-multi-market",
      "distance-nearest-first",
      "drafts",
      "duplicate-listing",
      "ebay-academy-multi-market",
      "ebay-ai-message-assistance",
      "ebay-business-supply",
      "ebay-collection-points-uk",
      "ebay-community-multi-market",
      "ebay-concierge",
      "ebay-deals-global",
      "ebay-export",
      "ebay-for-charity-multi-market",
      "ebay-fulfilment",
      "ebay-fulfilment-uk",
      "email-to-friend",
      "express-payouts-multi-currency",
      "fast-and-free",
      "fathers-day-gifts",
      "featured-listing",
      "feedback-reply-multi-market",
      "feedback-revision-request-multi-market",
      "form-1099-k-us",
      "free-2-day-shipping"
    ],
    "program_list": "1. Click-Through Rate (node_id: click-through-rate)\n2. Coded Coupons (node_id: coded-coupons)\n3. Coded Coupons (node_id: coded-coupons-multi-market)\n4. Codeless Coupons (node_id: codeless-coupons)\n5. Coins & Currency (node_id: coins-currency)\n6. Collectibles Price Guide (node_id: collectibles-price-guide)\n7. Collection Points (AU) (node_id: collection-points-au)\n8. Collections (node_id: collections)\n9. Combined Checkout (node_id: combined-checkout)\n10. Comics (node_id: comics)\n11. Condition Filter (node_id: condition-filter)\n12. Condition: New Sort (node_id: condition-new-sort)\n13. Curated Lists (node_id: curated-lists)\n14. Custom Template (node_id: custom-template)\n15. Delivered (node_id: delivered)\n16. Delivery Updates (node_id: delivery-updates)\n17. Description Template (node_id: description-template)\n18. Detailed Seller Ratings (DSRs) (node_id: detailed-seller-ratings-multi-market)\n19. DHL Paket (node_id: dhl-paket)\n20. Discounts Manager (node_id: discounts-manager)\n21. Discounts Manager (node_id: discounts-manager-multi-market)\n22. Distance: Nearest First (node_id: distance-nearest-first)\n23. Drafts (node_id: drafts)\n24. Duplicate Listing (node_id: duplicate-listing)\n25. eBay Academy (node_id: ebay-academy-multi-market)\n26. eBay.ai Message Assistance (node_id: ebay-ai-message-assistance)\n27. eBay Business Supply (node_id: ebay-business-supply)\n28. eBay Collection Points (node_id: ebay-collection-points-uk)\n29. eBay Community (node_id: ebay-community-multi-market)\n30. eBay Concierge (node_id: ebay-concierge)\n31. eBay Deals (node_id: ebay-deals-global)\n32. eBay Export (node_id: ebay-export)\n33. eBay for Charity (node_id: ebay-for-charity-multi-market)\n34. eBay Fulfilment (node_id: ebay-fulfilment)\n35. eBay Fulfilment (node_id: ebay-fulfilment-uk)\n36. Email to Friend (node_id: email-to-friend)\n37. Express Payouts (Multi-Currency) (node_id: express-payouts-multi-currency)\n38. Fast and Free (node_id: fast-and-free)\n39. Father's Day Gifts (node_id: fathers-day-gifts)\n40. Featured Listing (node_id: featured-listing)\n41. Feedback Reply (node_id: feedback-reply-multi-market)\n42. Feedback Revision Request (node_id: feedback-revision-request-multi-market)\n43. Form 1099-K (US) (node_id: form-1099-k-us)\n44. Free 2-day Shipping (node_id: free-2-day-shipping)"
  },
  {
    "batch_number": 22,
    "node_count": 44,
    "node_ids": [
      "free-3-day-shipping",
      "free-4-day-shipping",
      "free-shipping",
      "free-shipping-filter",
      "free-shipping-threshold",
      "gallery",
      "get-alerts",
      "gst-collection-australia",
      "hand-picked-collections",
      "helpful-review",
      "holiday-gift-guide",
      "html-editor",
      "image-search",
      "in-app-messaging",
      "in-app-qr-code",
      "in-transit",
      "inactive-listings",
      "item-comparison",
      "item-description-editor",
      "item-no-longer-available",
      "item-reviews",
      "item-specifics-filter",
      "items-watched",
      "label-printer",
      "linked-accounts-policy",
      "listing-confirmed-notification",
      "listing-enhancement",
      "listing-error",
      "listing-removal-notice",
      "live-chat-support",
      "location-filter",
      "login-alerts",
      "managed-display",
      "matching-categories",
      "message-buyer",
      "mobile-analytics",
      "mobile-photo-editor",
      "mobile-quick-list",
      "mobile-responsive-template",
      "mobile-responsive-templates",
      "more-from-this-seller",
      "mutual-feedback-withdrawal",
      "newly-listed",
      "no-bids"
    ],
    "program_list": "1. Free 3-day Shipping (node_id: free-3-day-shipping)\n2. Free 4-day Shipping (node_id: free-4-day-shipping)\n3. Free Shipping (node_id: free-shipping)\n4. Free Shipping Filter (node_id: free-shipping-filter)\n5. Free Shipping Threshold (node_id: free-shipping-threshold)\n6. Gallery (node_id: gallery)\n7. Get Alerts (node_id: get-alerts)\n8. GST Collection (Australia) (node_id: gst-collection-australia)\n9. Hand-Picked Collections (node_id: hand-picked-collections)\n10. Helpful Review (node_id: helpful-review)\n11. Holiday Gift Guide (node_id: holiday-gift-guide)\n12. HTML Editor (node_id: html-editor)\n13. Image Search (node_id: image-search)\n14. In-App Messaging (node_id: in-app-messaging)\n15. In-App QR Code (node_id: in-app-qr-code)\n16. In Transit (node_id: in-transit)\n17. Inactive Listings (node_id: inactive-listings)\n18. Item Comparison (node_id: item-comparison)\n19. Item Description Editor (node_id: item-description-editor)\n20. Item No Longer Available (node_id: item-no-longer-available)\n21. Item Reviews (node_id: item-reviews)\n22. Item Specifics Filter (node_id: item-specifics-filter)\n23. Items Watched (node_id: items-watched)\n24. Label Printer (node_id: label-printer)\n25. Linked Accounts Policy (node_id: linked-accounts-policy)\n26. Listing Confirmed Notification (node_id: listing-confirmed-notification)\n27. Listing Enhancement (node_id: listing-enhancement)\n28. Listing Error (node_id: listing-error)\n29. Listing Removal Notice (node_id: listing-removal-notice)\n30. Live Chat Support (node_id: live-chat-support)\n31. Location Filter (node_id: location-filter)\n32. Login Alerts (node_id: login-alerts)\n33. Managed Display (node_id: managed-display)\n34. Matching Categories (node_id: matching-categories)\n35. Message Buyer (node_id: message-buyer)\n36. Mobile Analytics (node_id: mobile-analytics)\n37. Mobile Photo Editor (node_id: mobile-photo-editor)\n38. Mobile Quick List (node_id: mobile-quick-list)\n39. Mobile-Responsive Template (node_id: mobile-responsive-template)\n40. Mobile Responsive Templates (node_id: mobile-responsive-templates)\n41. More From This Seller (node_id: more-from-this-seller)\n42. Mutual Feedback Withdrawal (node_id: mutual-feedback-withdrawal)\n43. Newly Listed (node_id: newly-listed)\n44. No Bids (node_id: no-bids)"
  },
  {
    "batch_number": 23,
    "node_count": 44,
    "node_ids": [
      "notify-me",
      "number-of-bids",
      "offer-accepted",
      "offer-declined",
      "offer-expires",
      "offer-history",
      "offer-sent",
      "offers-received",
      "offers-sent",
      "offers-to-watchers",
      "offers-to-watchers-multi-market",
      "offsite-ads-opt-out",
      "order-report",
      "order-updates",
      "out-for-delivery",
      "out-of-stock-control",
      "outbid-alert",
      "outbid-notice",
      "pay-in-4",
      "payment-failed",
      "payment-pending",
      "payment-processing",
      "payment-received",
      "phone-support",
      "photo-background-removal",
      "picture-zoom",
      "positive-feedback-percentage",
      "premium-placement",
      "price-alert",
      "price-drop-alert",
      "price-drop-alerts",
      "price-range",
      "price-suggestions",
      "print-coupons",
      "private-offers",
      "pro-seller-program",
      "pro-trader-program",
      "prohibited-restricted-items-by-country",
      "promote-similar-items",
      "promoted-brand",
      "promoted-to-international",
      "proseller-growth-program",
      "reserve-met",
      "reserve-not-met"
    ],
    "program_list": "1. Notify Me (node_id: notify-me)\n2. Number of Bids (node_id: number-of-bids)\n3. Offer Accepted (node_id: offer-accepted)\n4. Offer Declined (node_id: offer-declined)\n5. Offer Expires (node_id: offer-expires)\n6. Offer History (node_id: offer-history)\n7. Offer Sent (node_id: offer-sent)\n8. Offers Received (node_id: offers-received)\n9. Offers Sent (node_id: offers-sent)\n10. Offers to Watchers (node_id: offers-to-watchers)\n11. Offers to Watchers (node_id: offers-to-watchers-multi-market)\n12. Offsite Ads Opt Out (node_id: offsite-ads-opt-out)\n13. Order Report (node_id: order-report)\n14. Order Updates (node_id: order-updates)\n15. Out for Delivery (node_id: out-for-delivery)\n16. Out of Stock Control (node_id: out-of-stock-control)\n17. Outbid Alert (node_id: outbid-alert)\n18. Outbid Notice (node_id: outbid-notice)\n19. Pay in 4 (node_id: pay-in-4)\n20. Payment Failed (node_id: payment-failed)\n21. Payment Pending (node_id: payment-pending)\n22. Payment Processing (node_id: payment-processing)\n23. Payment Received (node_id: payment-received)\n24. Phone Support (node_id: phone-support)\n25. Photo Background Removal (node_id: photo-background-removal)\n26. Picture Zoom (node_id: picture-zoom)\n27. Positive Feedback Percentage (node_id: positive-feedback-percentage)\n28. Premium Placement (node_id: premium-placement)\n29. Price Alert (node_id: price-alert)\n30. Price Drop Alert (node_id: price-drop-alert)\n31. Price Drop Alerts (node_id: price-drop-alerts)\n32. Price Range (node_id: price-range)\n33. Price Suggestions (node_id: price-suggestions)\n34. Print Coupons (node_id: print-coupons)\n35. Private Offers (node_id: private-offers)\n36. Pro Seller Program (node_id: pro-seller-program)\n37. Pro Trader Program (node_id: pro-trader-program)\n38. Prohibited & Restricted Items by Country (node_id: prohibited-restricted-items-by-country)\n39. Promote Similar Items (node_id: promote-similar-items)\n40. Promoted Brand (node_id: promoted-brand)\n41. Promoted to International (node_id: promoted-to-international)\n42. ProSeller Growth Program (node_id: proseller-growth-program)\n43. Reserve Met (node_id: reserve-met)\n44. Reserve Not Met (node_id: reserve-not-met)"
  },
  {
    "batch_number": 24,
    "node_count": 45,
    "node_ids": [
      "return-approved",
      "return-received",
      "return-requested",
      "return-shipped",
      "return-to-sender",
      "returns-accepted-filter",
      "revise-listing",
      "rich-text-editor",
      "royal-mail-tracked-24",
      "sales-events",
      "save-for-later",
      "saved",
      "saved-drafts",
      "saved-payment-methods",
      "saved-seller",
      "schedule-start-time",
      "scheduled-listing",
      "search-filters",
      "search-standing-dashboard",
      "self-hosted-images",
      "seller-responded",
      "selling-coach",
      "session-duration",
      "session-expired",
      "shake-to-search",
      "ship-to-store",
      "shop-by-diagram",
      "shopping-updates",
      "show-only",
      "similar-items",
      "simple-delivery-uk",
      "spotlight-deals",
      "spring-clearance",
      "unique-visitors",
      "unread-messages",
      "vat-services-uk-eu",
      "views",
      "visitor-count",
      "visits",
      "visual-editor",
      "wata-grading",
      "watch-count",
      "watch-this-item",
      "watchers-count",
      "winning-notice"
    ],
    "program_list": "1. Return Approved (node_id: return-approved)\n2. Return Received (node_id: return-received)\n3. Return Requested (node_id: return-requested)\n4. Return Shipped (node_id: return-shipped)\n5. Return to Sender (node_id: return-to-sender)\n6. Returns Accepted Filter (node_id: returns-accepted-filter)\n7. Revise Listing (node_id: revise-listing)\n8. Rich Text Editor (node_id: rich-text-editor)\n9. Royal Mail Tracked 24 (node_id: royal-mail-tracked-24)\n10. Sales Events (node_id: sales-events)\n11. Save for Later (node_id: save-for-later)\n12. Saved (node_id: saved)\n13. Saved Drafts (node_id: saved-drafts)\n14. Saved Payment Methods (node_id: saved-payment-methods)\n15. Saved Seller (node_id: saved-seller)\n16. Schedule Start Time (node_id: schedule-start-time)\n17. Scheduled Listing (node_id: scheduled-listing)\n18. Search Filters (node_id: search-filters)\n19. Search Standing Dashboard (node_id: search-standing-dashboard)\n20. Self-Hosted Images (node_id: self-hosted-images)\n21. Seller Responded (node_id: seller-responded)\n22. Selling Coach (node_id: selling-coach)\n23. Session Duration (node_id: session-duration)\n24. Session Expired (node_id: session-expired)\n25. Shake to Search (node_id: shake-to-search)\n26. Ship to Store (node_id: ship-to-store)\n27. Shop by Diagram (node_id: shop-by-diagram)\n28. Shopping Updates (node_id: shopping-updates)\n29. Show Only (node_id: show-only)\n30. Similar Items (node_id: similar-items)\n31. Simple Delivery (node_id: simple-delivery-uk)\n32. Spotlight Deals (node_id: spotlight-deals)\n33. Spring Clearance (node_id: spring-clearance)\n34. Unique Visitors (node_id: unique-visitors)\n35. Unread Messages (node_id: unread-messages)\n36. VAT Services (UK/EU) (node_id: vat-services-uk-eu)\n37. Views (node_id: views)\n38. Visitor Count (node_id: visitor-count)\n39. Visits (node_id: visits)\n40. Visual Editor (node_id: visual-editor)\n41. WATA Grading (node_id: wata-grading)\n42. Watch Count (node_id: watch-count)\n43. Watch This Item (node_id: watch-this-item)\n44. Watchers Count (node_id: watchers-count)\n45. Winning Notice (node_id: winning-notice)"
  }
]